cybernova/__init__.py
cybernova/dns_analysis.py
cybernova/ip_analysis.py
cybernova/main.py
cybernova/port_scanner.py
cybernova/ssl_check.py
cybernova/vulnerability.py
tests/__init__.py
tests/main.py
tests/test_functions.py
cybernova-0.1.0.dist-info/LICENSE
cybernova-0.1.0.dist-info/METADATA
cybernova-0.1.0.dist-info/WHEEL
cybernova-0.1.0.dist-info/entry_points.txt
cybernova-0.1.0.dist-info/top_level.txt
cybernova-0.1.0.dist-info/RECORD
