Metadata-Version: 2.1
Name: cybernova
Version: 0.1.0
Summary: A suite of cybersecurity tools for network analysis and vulnerability scanning.
Home-page: https://github.com/Aniket-bhardwaj/CyberNova
Author: Aniket Bhardwaj
Author-email: aniket.bhardwaj0803@gmail.com
Classifier: Development Status :: 3 - Alpha
Classifier: Intended Audience :: Developers
Classifier: Topic :: Software Development :: Build Tools
Classifier: License :: OSI Approved :: MIT License
Classifier: Programming Language :: Python :: 3
Classifier: Programming Language :: Python :: 3.6
Classifier: Programming Language :: Python :: 3.7
Classifier: Programming Language :: Python :: 3.8
Classifier: Programming Language :: Python :: 3.9
Requires-Python: >=3.6
License-File: LICENSE
Requires-Dist: python-nmap >=0.7.1
Requires-Dist: python-whois >=0.9.4
Requires-Dist: dnspython >=0.6.30
